identity_plan_kit/__init__.py
identity_plan_kit/cli.py
identity_plan_kit/config.py
identity_plan_kit/kit.py
identity_plan_kit/migrations.py
identity_plan_kit/admin/__init__.py
identity_plan_kit/admin/auth.py
identity_plan_kit/admin/views.py
identity_plan_kit/auth/__init__.py
identity_plan_kit/auth/dependencies.py
identity_plan_kit/auth/uow.py
identity_plan_kit/auth/domain/__init__.py
identity_plan_kit/auth/domain/entities.py
identity_plan_kit/auth/domain/exceptions.py
identity_plan_kit/auth/dto/__init__.py
identity_plan_kit/auth/dto/requests.py
identity_plan_kit/auth/dto/responses.py
identity_plan_kit/auth/handlers/__init__.py
identity_plan_kit/auth/handlers/oauth_routes.py
identity_plan_kit/auth/models/__init__.py
identity_plan_kit/auth/models/refresh_token.py
identity_plan_kit/auth/models/user.py
identity_plan_kit/auth/models/user_provider.py
identity_plan_kit/auth/repositories/__init__.py
identity_plan_kit/auth/repositories/token_repo.py
identity_plan_kit/auth/repositories/user_repo.py
identity_plan_kit/auth/services/__init__.py
identity_plan_kit/auth/services/auth_service.py
identity_plan_kit/auth/services/oauth_service.py
identity_plan_kit/plans/__init__.py
identity_plan_kit/plans/dependencies.py
identity_plan_kit/plans/uow.py
identity_plan_kit/plans/cache/__init__.py
identity_plan_kit/plans/cache/plan_cache.py
identity_plan_kit/plans/cache/user_plan_cache.py
identity_plan_kit/plans/domain/__init__.py
identity_plan_kit/plans/domain/entities.py
identity_plan_kit/plans/domain/exceptions.py
identity_plan_kit/plans/dto/__init__.py
identity_plan_kit/plans/dto/responses.py
identity_plan_kit/plans/dto/usage.py
identity_plan_kit/plans/handlers/__init__.py
identity_plan_kit/plans/handlers/plan_routes.py
identity_plan_kit/plans/models/__init__.py
identity_plan_kit/plans/models/feature.py
identity_plan_kit/plans/models/feature_usage.py
identity_plan_kit/plans/models/plan.py
identity_plan_kit/plans/models/plan_limit.py
identity_plan_kit/plans/models/plan_permission.py
identity_plan_kit-0.3.7.dist-info/METADATA
identity_plan_kit-0.3.7.dist-info/WHEEL
identity_plan_kit-0.3.7.dist-info/entry_points.txt
identity_plan_kit-0.3.7.dist-info/RECORD
