Metadata-Version: 2.4
Name: identity-plan-kit
Version: 0.3.7
Summary: Modern FastAPI library for authentication, RBAC, subscription plans, and usage tracking
Author-email: harut <harut.avetisyan2002@gmail.com>
License: MIT
Keywords: authentication,fastapi,oauth,plans,rbac,subscription
Classifier: Development Status :: 3 - Alpha
Classifier: Framework :: FastAPI
Classifier: Intended Audience :: Developers
Classifier: License :: OSI Approved :: MIT License
Classifier: Programming Language :: Python :: 3
Classifier: Programming Language :: Python :: 3.11
Classifier: Programming Language :: Python :: 3.12
Classifier: Programming Language :: Python :: 3.13
Classifier: Topic :: Internet :: WWW/HTTP :: Session
Classifier: Topic :: Security
Classifier: Typing :: Typed
Requires-Python: >=3.11
Requires-Dist: alembic>=1.14.0
Requires-Dist: asyncpg>=0.30.0
Requires-Dist: authlib>=1.4.0
Requires-Dist: bcrypt<5.0.0,>=4.0.0
Requires-Dist: fastapi>=0.115.0
Requires-Dist: httpx>=0.28.0
Requires-Dist: itsdangerous>=2.2.0
Requires-Dist: orjson>=3.10.0
Requires-Dist: passlib[bcrypt]>=1.7.4
Requires-Dist: psycopg2-binary>=2.9.11
Requires-Dist: pydantic-settings>=2.0.0
Requires-Dist: pydantic[email]>=2.0.0
Requires-Dist: python-jose[cryptography]>=3.3.0
Requires-Dist: rich>=13.0.0
Requires-Dist: slowapi>=0.1.9
Requires-Dist: sqlalchemy[asyncio]>=2.0.0
Requires-Dist: structlog>=24.0.0
Requires-Dist: tenacity>=9.0.0
Requires-Dist: typer>=0.12.0
Requires-Dist: uuid-utils>=0.10.0
Provides-Extra: admin
Requires-Dist: sqladmin>=0.20.0; extra == 'admin'
Provides-Extra: cli
Requires-Dist: python-dotenv>=1.0.0; extra == 'cli'
Provides-Extra: dev
Requires-Dist: bump-my-version>=0.26.0; extra == 'dev'
Requires-Dist: httpx>=0.28.0; extra == 'dev'
Requires-Dist: mypy>=1.13.0; extra == 'dev'
Requires-Dist: pre-commit>=4.0.0; extra == 'dev'
Requires-Dist: pytest-asyncio>=0.24.0; extra == 'dev'
Requires-Dist: pytest-cov>=6.0.0; extra == 'dev'
Requires-Dist: pytest>=8.0.0; extra == 'dev'
Requires-Dist: ruff>=0.8.0; extra == 'dev'
Requires-Dist: testcontainers[postgres]>=4.0.0; extra == 'dev'
Provides-Extra: loadtest
Requires-Dist: faker>=28.0.0; extra == 'loadtest'
Requires-Dist: locust>=2.29.0; extra == 'loadtest'
Provides-Extra: metrics
Requires-Dist: prometheus-client>=0.20.0; extra == 'metrics'
